.hgtags
LICENSE
MANIFEST.in
README.txt
VERSION
confargparse.py
setup.py
ConfArgParse.egg-info/PKG-INFO
ConfArgParse.egg-info/SOURCES.txt
ConfArgParse.egg-info/dependency_links.txt
ConfArgParse.egg-info/requires.txt
ConfArgParse.egg-info/top_level.txt