Metadata-Version: 1.1
Name: ConfArgParse
Version: 1.1.20
Summary: An integrated argument/configuration file parser that follows the syntax of argparser
Home-page: https://bitbucket.org/swamidass/confargparse/
Author: S. Joshua Swamidass
Author-email: swamidass@gmail.com
License: UNKNOWN
Platform: UNKNOWN
Classifier: Development Status :: 4 - Beta
Classifier: License :: OSI Approved :: MIT License
Classifier: License :: Free for non-commercial use
Classifier: Natural Language :: English
Classifier: Programming Language :: Python
Classifier: Intended Audience :: Developers
